{
  "checked_at": "2026-06-01T22:01:04Z",
  "alerts": [
    {
      "severity": "high",
      "kind": "position_break",
      "text": "FBL gapped down -10.0% today"
    },
    {
      "severity": "high",
      "kind": "position_break",
      "text": "META gapped down -5.1% today"
    },
    {
      "severity": "low",
      "kind": "watchlist_entry",
      "text": "NOW at $135.86 - within buy zone of yesterday's breakout setup ($135.97)"
    },
    {
      "severity": "low",
      "kind": "watchlist_entry",
      "text": "MDB at $403.88 - within buy zone of yesterday's breakout setup ($394.27)"
    },
    {
      "severity": "low",
      "kind": "watchlist_entry",
      "text": "ORCL at $248.15 - within buy zone of yesterday's breakout setup ($244.10)"
    },
    {
      "severity": "low",
      "kind": "watchlist_entry",
      "text": "COST RSI 32 - oversold reversal in progress (from yesterday's bucket)"
    },
    {
      "severity": "med",
      "kind": "watchlist_entry",
      "text": "ARM in entry zone $406.94-$429.11 (plan: stop $365.37, target $523.33, hold 2-3 weeks)"
    },
    {
      "severity": "med",
      "kind": "watchlist_entry",
      "text": "LLY in entry zone $1065.50-$1091.30 (plan: stop $1017.13, target $1200.94, hold 2-3 weeks)"
    },
    {
      "severity": "med",
      "kind": "watchlist_entry",
      "text": "KLAC in entry zone $1901.71-$1968.06 (plan: stop $1777.30, target $2250.06, hold 2-3 weeks)"
    },
    {
      "severity": "med",
      "kind": "watchlist_entry",
      "text": "GEV in entry zone $923.47-$967.52 (plan: stop $857.40, target $1121.68, hold 2-3 weeks)"
    },
    {
      "severity": "med",
      "kind": "watchlist_entry",
      "text": "LUNR in entry zone $37.45-$41.86 (plan: stop $29.18, target $60.61, hold 2-3 weeks)"
    },
    {
      "severity": "med",
      "kind": "watchlist_entry",
      "text": "IWM in entry zone $287.69-$291.71 (plan: stop $280.16, target $308.78, hold 2-3 weeks)"
    },
    {
      "severity": "med",
      "kind": "watchlist_entry",
      "text": "AVGO in entry zone $454.76-$468.43 (plan: stop $429.12, target $526.55, hold 2-3 weeks)"
    },
    {
      "severity": "med",
      "kind": "watchlist_entry",
      "text": "ONTO in entry zone $244.19-$258.84 (plan: stop $222.21, target $310.12, hold 2-3 weeks)"
    },
    {
      "severity": "med",
      "kind": "watchlist_entry",
      "text": "SMCI in entry zone $44.96-$47.22 (plan: stop $40.70, target $56.87, hold 2-3 weeks)"
    },
    {
      "severity": "med",
      "kind": "watchlist_entry",
      "text": "BEAM in entry zone $30.86-$32.35 (plan: stop $28.06, target $38.70, hold 2-3 weeks)"
    },
    {
      "severity": "med",
      "kind": "watchlist_entry",
      "text": "ETN in entry zone $398.19-$408.81 (plan: stop $378.28, target $453.94, hold 2-3 weeks)"
    },
    {
      "severity": "med",
      "kind": "watchlist_entry",
      "text": "TT in entry zone $439.20-$450.39 (plan: stop $422.42, target $489.54, hold 2-3 weeks)"
    },
    {
      "severity": "med",
      "kind": "watchlist_entry",
      "text": "XBI in entry zone $133.31-$136.01 (plan: stop $128.25, target $147.48, hold 2-3 weeks)"
    },
    {
      "severity": "med",
      "kind": "watchlist_entry",
      "text": "COST in entry zone $921.05-$947.24 (plan: stop $881.77, target $1038.89, hold 2-3 weeks)"
    },
    {
      "severity": "med",
      "kind": "watchlist_entry",
      "text": "NEE in entry zone $82.50-$84.83 (plan: stop $79.00, target $92.99, hold 2-3 weeks)"
    },
    {
      "severity": "med",
      "kind": "watchlist_entry",
      "text": "XLC in entry zone $114.56-$115.99 (plan: stop $112.42, target $120.99, hold 2-3 weeks)"
    },
    {
      "severity": "med",
      "kind": "watchlist_entry",
      "text": "XLE in entry zone $56.27-$57.55 (plan: stop $54.35, target $62.03, hold 2-3 weeks)"
    },
    {
      "severity": "med",
      "kind": "watchlist_entry",
      "text": "URA in entry zone $48.98-$51.06 (plan: stop $45.86, target $58.34, hold 2-3 weeks)"
    },
    {
      "severity": "med",
      "kind": "watchlist_entry",
      "text": "SNOW in entry zone $274.09-$285.58 (plan: stop $252.55, target $334.40, hold 2-3 weeks)"
    },
    {
      "severity": "med",
      "kind": "watchlist_entry",
      "text": "MDB in entry zone $386.91-$406.53 (plan: stop $350.12, target $489.92, hold 2-3 weeks)"
    },
    {
      "severity": "med",
      "kind": "watchlist_entry",
      "text": "FSLR in entry zone $301.06-$313.64 (plan: stop $277.46, target $367.13, hold 2-3 weeks)"
    },
    {
      "severity": "med",
      "kind": "watchlist_entry",
      "text": "OKTA in entry zone $137.10-$142.92 (plan: stop $126.18, target $167.67, hold 2-3 weeks)"
    },
    {
      "severity": "med",
      "kind": "watchlist_entry",
      "text": "ORCL in entry zone $240.88-$249.47 (plan: stop $224.78, target $285.97, hold 2-3 weeks)"
    },
    {
      "severity": "med",
      "kind": "watchlist_entry",
      "text": "NOW in entry zone $133.72-$139.73 (plan: stop $122.45, target $165.27, hold 2-3 weeks)"
    },
    {
      "severity": "med",
      "kind": "watchlist_entry",
      "text": "CRM in entry zone $205.60-$212.87 (plan: stop $191.97, target $243.77, hold 2-3 weeks)"
    },
    {
      "severity": "med",
      "kind": "watchlist_entry",
      "text": "SOFI in entry zone $17.97-$18.64 (plan: stop $16.70, target $21.52, hold 2-3 weeks)"
    },
    {
      "severity": "med",
      "kind": "watchlist_entry",
      "text": "HUBS in entry zone $253.73-$265.87 (plan: stop $230.97, target $317.46, hold 2-3 weeks)"
    },
    {
      "severity": "med",
      "kind": "watchlist_entry",
      "text": "QCOM in entry zone $226.02-$240.92 (plan: stop $198.09, target $304.23, hold 2-3 weeks)"
    },
    {
      "severity": "med",
      "kind": "watchlist_entry",
      "text": "XLK in entry zone $194.18-$197.70 (plan: stop $187.58, target $212.66, hold 2-3 weeks)"
    },
    {
      "severity": "med",
      "kind": "watchlist_entry",
      "text": "DDOG in entry zone $273.95-$283.25 (plan: stop $256.51, target $322.78, hold 2-3 weeks)"
    },
    {
      "severity": "med",
      "kind": "watchlist_entry",
      "text": "PATH in entry zone $12.57-$13.21 (plan: stop $11.37, target $15.93, hold 2-3 weeks)"
    },
    {
      "severity": "med",
      "kind": "watchlist_entry",
      "text": "ZS in entry zone $147.84-$158.98 (plan: stop $126.96, target $206.31, hold 2-3 weeks)"
    },
    {
      "severity": "med",
      "kind": "watchlist_entry",
      "text": "XLY in entry zone $116.65-$118.66 (plan: stop $113.63, target $125.71, hold 2-3 weeks)"
    }
  ],
  "fired_plans": {
    "GEV|1124.52": "2026-06-01",
    "LUNR|60.39": "2026-06-01",
    "MU|1261.76": "2026-06-01",
    "ONTO|307.47": "2026-06-01",
    "BEAM|38.61": "2026-06-01",
    "ETN|452.76": "2026-06-01",
    "XBI|146.92": "2026-06-01",
    "DIA|528.12": "2026-06-01",
    "QBTS|40.57": "2026-06-01",
    "AFRM|88.33": "2026-06-01",
    "NOW|160.06": "2026-06-01",
    "ESTC|77.8": "2026-06-01",
    "S|21.23": "2026-06-01",
    "ARM|523.33": "2026-06-01",
    "LLY|1200.94": "2026-06-01",
    "KLAC|2250.06": "2026-06-01",
    "GEV|1121.68": "2026-06-01",
    "LUNR|60.61": "2026-06-01",
    "IWM|308.78": "2026-06-01",
    "AVGO|526.55": "2026-06-01",
    "ONTO|310.12": "2026-06-01",
    "SMCI|56.87": "2026-06-01",
    "BEAM|38.7": "2026-06-01",
    "ETN|453.94": "2026-06-01",
    "TT|489.54": "2026-06-01",
    "XBI|147.48": "2026-06-01",
    "COST|1038.89": "2026-06-01",
    "NEE|92.99": "2026-06-01",
    "XLC|120.99": "2026-06-01",
    "XLE|62.03": "2026-06-01",
    "URA|58.34": "2026-06-01",
    "SNOW|334.4": "2026-06-01",
    "MDB|489.92": "2026-06-01",
    "FSLR|367.13": "2026-06-01",
    "OKTA|167.67": "2026-06-01",
    "ORCL|285.97": "2026-06-01",
    "NOW|165.27": "2026-06-01",
    "CRM|243.77": "2026-06-01",
    "SOFI|21.52": "2026-06-01",
    "HUBS|317.46": "2026-06-01",
    "QCOM|304.23": "2026-06-01",
    "XLK|212.66": "2026-06-01",
    "DDOG|322.78": "2026-06-01",
    "PATH|15.93": "2026-06-01",
    "ZS|206.31": "2026-06-01",
    "XLY|125.71": "2026-06-01"
  }
}